cache/__init__.py
cache/holder/RedisCacheHolder.py
cache/holder/__init__.py
cache/provider/RedisCacheProvider.py
cache/provider/RedisCacheProviderWithHash.py
cache/provider/__init__.py
cache/utility/BigFloat_utility.py
cache/utility/__init__.py
persuader_technology_automata_redis-0.3.8.dist-info/LICENSE
persuader_technology_automata_redis-0.3.8.dist-info/METADATA
persuader_technology_automata_redis-0.3.8.dist-info/WHEEL
persuader_technology_automata_redis-0.3.8.dist-info/top_level.txt
persuader_technology_automata_redis-0.3.8.dist-info/RECORD
