Metadata-Version: 2.1
Name: persuader-technology-automata-redis
Version: 0.3.8
Summary: Automata Redis
Author: Persuader Technology
Author-email: software@persuader.technology
License: UNLICENSE
Classifier: Programming Language :: Python :: 3
License-File: LICENSE
Requires-Dist: redis (==4.3.4)
Requires-Dist: persuader-technology-automata-core (>=0.6.0)
Requires-Dist: persuader-technology-automata-utilities (>=0.2.1)
Requires-Dist: persuader-technology-automata-logger (>=0.0.5)
